<?xml version="1.0" encoding="UTF-8"?>
<pageaomount>
<jan_cd>1281</jan_cd>
<agt_product_cd>0</agt_product_cd>
<agt_cd>LMJ</agt_cd>
<product_type>93</product_type>
<product_name><![CDATA[ＸＥＮＡ　バイク盗難防止高性能アラーム]]></product_name>
<product_sub_title/>
<catchcopy><![CDATA[物騒な世の中、自分のバイクは自分で守る！小型ボディから110dbの大音量アラーム。なんとっ、定価の１６％ＯＦＦのギリギリ価格でご提供。]]></catchcopy>
<price_catch/>
<opening><![CDATA[20020815]]></opening>
<specword/>
<moreinfo/>
<c_coment><![CDATA[0]]></c_coment>
<body><![CDATA[知る人ぞ知る、画期的でスタイリッシュなバイク専用アラームです。
赤外線センターとマイクロプロセッサをリンクさせることによって実現
した次世代セキュリティシステムは、ディスクロック方式を採用。
ブレーキディスクに簡単に装着でき、振動や傾きを検知すると警告音を
2回発し、その後110dbという大音量の警報音を約10秒間発します。
業界でも有名なこの商品は、雑誌等で大きく取り上げられおてり、急速
にシェアーを拡大しつつあります。

装着法はいたって簡単！ブレーキローターに穴があるタイプのバイクな
らほとんどのメーカー、車種に対応しています。いままでのように、フ
ェンスや電信柱に頼らなくても済むので、周囲に何もない場所での駐車
も安心。
さらに、前輪と後輪をダブルでロックすれば効果は二倍！いままでのロ
ックはそのままに、「ＸＥＮＡ」で愛車を守りましょう。

適合モデル：ディスクローターに放射線状の穴がある車種
　　　　　　それ以外はメールにてお問い合わせください
警報：１１０ｄｂアラーム
キー：対ピッキング・ディンプルキー（３本つき）
電池：ＬＲ４４ボタン型電池６個（通常使用で約６ヶ月使用可能）
　　　商品発送時に同電池６個付属
]]></body>
<havealt>1</havealt>
<price>0</price>
<pricestr><![CDATA[0]]></pricestr>
<tax>5</tax>
<taxstr><![CDATA[5]]></taxstr>
<sending/>
<sending_tax>5</sending_tax>
<sending_calc_unit/>
<first_name><![CDATA[ラストミニット・ドットコム]]></first_name>
<lastname/>
<linkedurl/>
</pageaomount>
