<?xml version="1.0" encoding="UTF-8"?>
<pageaomount>
<jan_cd>1490</jan_cd>
<agt_product_cd>RS007</agt_product_cd>
<agt_cd>JSE</agt_cd>
<product_type>93</product_type>
<product_name><![CDATA[福猫グッズ「レター・ラック」]]></product_name>
<product_sub_title/>
<catchcopy><![CDATA[壁に掛けてレターやメモを収納しよう！福猫シリーズ第４弾はレター・ラックのご紹介です。]]></catchcopy>
<price_catch/>
<opening><![CDATA[20021002]]></opening>
<specword/>
<moreinfo/>
<c_coment><![CDATA[■この商品は、提携サプライヤー「株式会社ジェイセレクション」から
　の配送になります。
■この商品の送料は全国一律500円です。
■商品は、お申し込みの翌日から３営業日（土日祝を除く）以内に発送
　いたします。
■お届け時間帯をご指定の場合は、次の選択肢の中からお選びいただき
　下の「ご記入欄」にご記入ください。
　選択肢：　1.午前　2.12-16時　3.16-19時　4.19-22時
　ご記入がない場合は、「指定なし」とさせていただきます。
■商品の返品、交換は、配送中の破損等に限りお受けいたします。その
　場合は、商品を受領した後７日以内に送料受取人払いでご返送くださ
　い。
]]></c_coment>
<body><![CDATA[壁飾りとしても可愛い「レター・ラック」です。
風水で縁起がいいとされる色を水玉模様にあしらいました。まさに開運
の福猫レター・ラックです。
仕上げはウレタン塗装なので、軽い水拭きもＯＫです。
お友達の引っ越し祝いや、猫大好きな方へのちょっとしたプレゼントと
して最適のアイテムです。

●材質：和紙
●表面：ウレタン塗装
●色：白
●サイズ：縦18cm×横15cm×厚さ2.5cm]]></body>
<havealt>1</havealt>
<price>2500</price>
<pricestr><![CDATA[2,500]]></pricestr>
<tax>5</tax>
<taxstr><![CDATA[5]]></taxstr>
<sending/>
<sending_tax>5</sending_tax>
<sending_calc_unit/>
<first_name><![CDATA[株式会社ジェイセレクション]]></first_name>
<lastname><![CDATA[松田　壽美子]]></lastname>
<linkedurl/>
</pageaomount>
